tests/__init__.py
tests/test_expression.py
jsonatago-0.2.6.dist-info/WHEEL
jsonatago-0.2.6.dist-info/LICENSE.txt
jsonatago-0.2.6.dist-info/METADATA
jsonatago-0.2.6.dist-info/RECORD
jsonatago-0.2.6.dist-info/top_level.txt
jsonatago/jsonatago.py
jsonatago/__init__.py
jsonatago/jsonatago_capi.pypy38-pp73-x86_64-linux-gnu.so
jsonatago/jsonatago_capi.pypy38-pp73-x86_64-linux-gnu.h
