Metadata-Version: 2.1
Name: jsonatago
Version: 0.2.6
Summary: Your package description here
Home-page: https://github.com/rados4y/jsonatago
Classifier: Development Status :: 3 - Alpha
Requires-Python: >=3.8
License-File: LICENSE.txt
